pytexreport/__init__.py
pytexreport/py.typed
pytexreport/pytexreport.py
pytexreport/style/__init__.py
pytexreport/style/basicHomework/__init__.py
pytexreport/style/basicHomework/basicHomework.cls
pytexreport/style/basicHomework/basicHomework.py
pytexreport/style/basicReport/__init__.py
pytexreport/style/basicReport/basicReport.py
pytexreport/style/ieeeConference/__init__.py
pytexreport/style/ieeeConference/ieeeConference.cls
pytexreport/style/ieeeConference/ieeeConference.py
pytexreport-0.1.0.dist-info/METADATA
pytexreport-0.1.0.dist-info/WHEEL
pytexreport-0.1.0.dist-info/RECORD
