Metadata-Version: 2.1
Name: pytexreport
Version: 0.1.0
Summary: A short description of the project
Home-page: https://nkalis.github.io/pytexreport
License: MIT
Author: nkalis
Author-email: n.kalis98@gmail.com
Requires-Python: >=3.8,<3.11
Classifier: Development Status :: 4 - Beta
Classifier: Intended Audience :: Developers
Classifier: License :: OSI Approved :: MIT License
Classifier: Operating System :: OS Independent
Classifier: Programming Language :: Python
Classifier: Programming Language :: Python :: 3
Classifier: Programming Language :: Python :: 3.8
Classifier: Programming Language :: Python :: 3.9
Classifier: Programming Language :: Python :: 3.10
Classifier: Programming Language :: Python :: 3.7
Classifier: Topic :: Software Development :: Libraries :: Python Modules
Classifier: Typing :: Typed
Requires-Dist: latexify-py (>=0.2.0,<0.3.0)
Requires-Dist: loguru (>=0.7.0,<0.8.0)
Requires-Dist: matplotlib (>=3.7.1,<4.0.0)
Requires-Dist: pylatex (>=1.4.1,<2.0.0)
Project-URL: Documentation, https://nkalis.github.io/pytexreport
Project-URL: Repository, https://github.com/nkalis/pytexreport
